aiohttp_splunk_logging
