Metadata-Version: 1.1
Name: aiohttp-splunk-logging
Version: 1.0.4
Summary: Splunk Logging integration for aiohttp applications
Home-page: UNKNOWN
Author: Bo Arnold
Author-email: deryl.arnold@walmart.com
License: MIT
Keywords: splunk,logging,HTTP Event Collector
Platform: UNKNOWN
Classifier: Development Status :: 3 - Alpha
Classifier: Topic :: Software Development :: Build Tools
Classifier: License :: OSI Approved :: MIT License
Classifier: Programming Language :: Python :: 2
Classifier: Programming Language :: Python :: 2.6
Classifier: Programming Language :: Python :: 2.7
Classifier: Programming Language :: Python :: 3
